README.rst
setup.py
superprocess/__init__.py
superprocess/base.py
superprocess/pipe.py
superprocess/redirect.py
superprocess/remote.py
superprocess/utils.py
superprocess.egg-info/PKG-INFO
superprocess.egg-info/SOURCES.txt
superprocess.egg-info/dependency_links.txt
superprocess.egg-info/top_level.txt