Metadata-Version: 1.1
Name: superprocess
Version: 0.2.0
Summary: subprocess-like API for starting local and remote processes
Home-page: https://bitbucket.org/stevedrake/superprocess
Author: Stephen Drake
Author-email: steve@synergyconsultingnz.com
License: Apache 2.0
Keywords: subprocess ssh
Platform: UNKNOWN
Classifier: Development Status :: 4 - Beta
Classifier: Intended Audience :: Developers
Classifier: License :: OSI Approved :: Apache Software License
Classifier: Programming Language :: Python :: 2
Classifier: Programming Language :: Python :: 2.6
Classifier: Programming Language :: Python :: 2.7
Classifier: Programming Language :: Python :: 3
Classifier: Programming Language :: Python :: 3.4
